{
    "questions": [
        {
            "id": "q1",
            "number": 1,
            "question": "The following are the marks (out of 100) of 60 students in mathematics:<br>16, 13, 5, 80, 86, 7, 51, 48, 24, 56, 70, 19, 61, 17, 16, 36, 34, 42, 34, 35, 72, 55, 75, 31, 52, 28, 72, 97, 74, 45, 62, 68, 86, 35, 85, 36, 81, 75, 55, 26, 95, 31, 7, 78, 92, 62, 52, 56, 15, 63, 25, 36, 54, 44, 47, 27, 72, 17, 4, 30.<br>Construct a grouped frequency distribution table with width 10 of each class starting from 0 - 9.",
            "answer": "See table below",
            "solution": "<div class=\"q-table-container\"><table class=\"q-table\"><thead><tr><th>Class Interval</th><th>Tally Marks</th><th>Frequency</th></tr></thead><tbody><tr><td>0 - 9</td><td>||||</td><td>4</td></tr><tr><td>10 - 19</td><td>|||| |||</td><td>8</td></tr><tr><td>20 - 29</td><td>||||</td><td>5</td></tr><tr><td>30 - 39</td><td>|||| ||||</td><td>10</td></tr><tr><td>40 - 49</td><td>||||</td><td>5</td></tr><tr><td>50 - 59</td><td>|||| |||</td><td>8</td></tr><tr><td>60 - 69</td><td>||||</td><td>5</td></tr><tr><td>70 - 79</td><td>|||| |||</td><td>8</td></tr><tr><td>80 - 89</td><td>|||| |</td><td>6</td></tr><tr><td>90 - 99</td><td>|</td><td>1</td></tr><tr><td><strong>Total</strong></td><td></td><td><strong>60</strong></td></tr></tbody></table></div>"
        },
        {
            "id": "q2",
            "number": 2,
            "question": "Refer to Q1 above. Construct a grouped frequency distribution table with width 10 of each class, in such a way that one of the classes is 10 - 20 (20 not included).",
            "answer": "See table below",
            "solution": "<div class=\"q-table-container\"><table class=\"q-table\"><thead><tr><th>Class Interval</th><th>Frequency</th></tr></thead><tbody><tr><td>0 - 10</td><td>4</td></tr><tr><td>10 - 20</td><td>8</td></tr><tr><td>20 - 30</td><td>5</td></tr><tr><td>30 - 40</td><td>10</td></tr><tr><td>40 - 50</td><td>5</td></tr><tr><td>50 - 60</td><td>8</td></tr><tr><td>60 - 70</td><td>5</td></tr><tr><td>70 - 80</td><td>8</td></tr><tr><td>80 - 90</td><td>6</td></tr><tr><td>90 - 100</td><td>1</td></tr><tr><td><strong>Total</strong></td><td><strong>60</strong></td></tr></tbody></table></div>"
        },
        {
            "id": "q3",
            "number": 3,
            "question": "Draw a histogram of the following distribution:<br>Heights (in cm): 150-153, 153-156, 156-159, 159-162, 162-165, 165-168<br>Number of students: 7, 8, 14, 10, 6, 5",
            "diagram": "<div class=\"q-table-container\"><table class=\"q-table\"><tr><th>Heights (in cm)</th><td>150-153</td><td>153-156</td><td>156-159</td><td>159-162</td><td>162-165</td><td>165-168</td></tr><tr><th>No. of Students</th><td>7</td><td>8</td><td>14</td><td>10</td><td>6</td><td>5</td></tr></table></div>",
            "answer": "Histogram required",
            "solution": "Represent the class intervals (Heights) on the x-axis and the frequency (Number of students) on the y-axis. Since the scale on the x-axis starts at 150, a kink (break) is shown near the origin.<br>Draw rectangles with bases as class intervals and heights corresponding to their frequencies."
        },
        {
            "id": "q4",
            "number": 4,
            "question": "Draw a histogram to represent the following grouped frequency distribution:<br>Ages (in years): 20-24, 25-29, 30-34, 35-39, 40-44, 45-49, 50-54<br>Number of teachers: 10, 28, 32, 48, 50, 35, 12",
            "diagram": "<div class=\"q-table-container\"><table class=\"q-table\"><tr><th>Ages (in years)</th><td>20-24</td><td>25-29</td><td>30-34</td><td>35-39</td><td>40-44</td><td>45-49</td><td>50-54</td></tr><tr><th>No. of Teachers</th><td>10</td><td>28</td><td>32</td><td>48</td><td>50</td><td>35</td><td>12</td></tr></table></div>",
            "answer": "Convert to exclusive form first",
            "solution": "The class intervals are inclusive. Convert them to exclusive form by subtracting 0.5 from the lower limit and adding 0.5 to the upper limit.<br><strong>Modified Table:</strong><br><div class=\"q-table-container\"><table class=\"q-table\"><thead><tr><th>Age (in years)</th><th>No. of Teachers</th></tr></thead><tbody><tr><td>19.5 - 24.5</td><td>10</td></tr><tr><td>24.5 - 29.5</td><td>28</td></tr><tr><td>29.5 - 34.5</td><td>32</td></tr><tr><td>34.5 - 39.5</td><td>48</td></tr><tr><td>39.5 - 44.5</td><td>50</td></tr><tr><td>44.5 - 49.5</td><td>35</td></tr><tr><td>49.5 - 54.5</td><td>12</td></tr></tbody></table></div><br>Draw the histogram using these modified class intervals."
        },
        {
            "id": "q5",
            "number": 5,
            "question": "The lengths of 62 leaves of a plant are measured in millimetres and the data is represented in the following table:<br>Length (in mm): 118-126, 127-135, 136-144, 145-153, 154-162, 163-171, 172-180<br>Number of leaves: 8, 10, 12, 17, 7, 5, 3<br>Draw a histogram to represent the data above.",
            "diagram": "<div class=\"q-table-container\"><table class=\"q-table\"><tr><th>Length (mm)</th><td>118-126</td><td>127-135</td><td>136-144</td><td>145-153</td><td>154-162</td><td>163-171</td><td>172-180</td></tr><tr><th>No. of Leaves</th><td>8</td><td>10</td><td>12</td><td>17</td><td>7</td><td>5</td><td>3</td></tr></table></div>",
            "answer": "Convert to exclusive form first",
            "solution": "The intervals are discontinuous. Gap = 1. Adjustment = 0.5.<br><strong>Modified Intervals:</strong><br>117.5 - 126.5 (8)<br>126.5 - 135.5 (10)<br>135.5 - 144.5 (12)<br>144.5 - 153.5 (17)<br>153.5 - 162.5 (7)<br>162.5 - 171.5 (5)<br>171.5 - 180.5 (3)<br>Draw the histogram with these intervals."
        },
        {
            "id": "q6",
            "number": 6,
            "question": "The marks obtained (out of 100) by a class of 80 students are given below:<br>Marks: 10-20, 20-30, 30-50, 50-70, 70-100<br>Number of students: 6, 17, 15, 16, 26<br>Construct a histogram to represent the data above.",
            "diagram": "<div class=\"q-table-container\"><table class=\"q-table\"><tr><th>Marks</th><td>10-20</td><td>20-30</td><td>30-50</td><td>50-70</td><td>70-100</td></tr><tr><th>Students</th><td>6</td><td>17</td><td>15</td><td>16</td><td>26</td></tr></table></div>",
            "answer": "Adjust frequencies for varying widths",
            "solution": "The class widths vary. Minimum class width = 10.<br><strong>Adjusted Frequency = (Frequency / Class Width) × Min Class Width</strong><br><div class=\"q-table-container\"><table class=\"q-table\"><thead><tr><th>Marks</th><th>Width</th><th>Frequency</th><th>Adjusted Frequency</th></tr></thead><tbody><tr><td>10 - 20</td><td>10</td><td>6</td><td>$\\frac{6}{10} \\times 10 = 6$</td></tr><tr><td>20 - 30</td><td>10</td><td>17</td><td>$\\frac{17}{10} \\times 10 = 17$</td></tr><tr><td>30 - 50</td><td>20</td><td>15</td><td>$\\frac{15}{20} \\times 10 = 7.5$</td></tr><tr><td>50 - 70</td><td>20</td><td>16</td><td>$\\frac{16}{20} \\times 10 = 8$</td></tr><tr><td>70 - 100</td><td>30</td><td>26</td><td>$\\frac{26}{30} \\times 10 \\approx 8.67$</td></tr></tbody></table></div><br>Draw the histogram with heights corresponding to the adjusted frequencies."
        },
        {
            "id": "q7",
            "number": 7,
            "question": "Following table shows a frequency distribution for the speed of cars passing through at a particular spot on a highway:<br>Class interval (km/h): 30-40, 40-50, 50-60, 60-70, 70-80, 80-90, 90-100<br>Frequency: 3, 6, 25, 65, 50, 28, 14<br>Draw a histogram and frequency polygon representing the data above.",
            "diagram": "<div class=\"q-table-container\"><table class=\"q-table\"><tr><th>Speed (km/h)</th><td>30-40</td><td>40-50</td><td>50-60</td><td>60-70</td><td>70-80</td><td>80-90</td><td>90-100</td></tr><tr><th>Frequency</th><td>3</td><td>6</td><td>25</td><td>65</td><td>50</td><td>28</td><td>14</td></tr></table></div>",
            "answer": "Histogram and Frequency Polygon",
            "solution": "1. Draw the histogram with class intervals on x-axis and frequency on y-axis.<br>2. Mark the mid-points of the top of the rectangles.<br>3. Join these mid-points by line segments to get the frequency polygon.<br>4. To complete the polygon, join the first and last points to the mid-points of the imaginary intervals 20-30 and 100-110 with frequency 0."
        },
        {
            "id": "q8",
            "number": 8,
            "question": "Refer to Q. 7: Draw the frequency polygon representing the above data without drawing the histogram.",
            "answer": "Use Class Marks",
            "solution": "Calculate the class marks ($x_i$) for each interval: $x_i = \\frac{\\text{Upper} + \\text{Lower}}{2}$.<br><div class=\"q-table-container\"><table class=\"q-table\"><thead><tr><th>Class Interval</th><th>Class Mark ($x_i$)</th><th>Frequency</th></tr></thead><tbody><tr><td>30 - 40</td><td>35</td><td>3</td></tr><tr><td>40 - 50</td><td>45</td><td>6</td></tr><tr><td>50 - 60</td><td>55</td><td>25</td></tr><tr><td>60 - 70</td><td>65</td><td>65</td></tr><tr><td>70 - 80</td><td>75</td><td>50</td></tr><tr><td>80 - 90</td><td>85</td><td>28</td></tr><tr><td>90 - 100</td><td>95</td><td>14</td></tr></tbody></table></div><br>Plot points $(35, 3), (45, 6), \\dots, (95, 14)$. Join them. Also join to $(25, 0)$ and $(105, 0)$."
        },
        {
            "id": "q9",
            "number": 9,
            "question": "Following table gives the distribution of students of sections A and B of a class according to the marks obtained by them.<br><strong>Section A:</strong> 0-15 (5), 15-30 (12), 30-45 (28), 45-60 (30), 60-75 (35), 75-90 (13)<br><strong>Section B:</strong> 0-15 (3), 15-30 (16), 30-45 (25), 45-60 (27), 60-75 (40), 75-90 (10)<br>Represent the marks of the students of both the sections on the same graph by two frequency polygons. What do you observe?",
            "answer": "Comparison of performance",
            "solution": "Calculate class marks for both sections.<br>Class Marks: 7.5, 22.5, 37.5, 52.5, 67.5, 82.5.<br>Plot points for Section A: $(7.5, 5), (22.5, 12), \\dots$<br>Plot points for Section B: $(7.5, 3), (22.5, 16), \\dots$<br><strong>Observation:</strong> Section A generally has better performance in the higher marks range (45-75), while Section B peaks at 60-75 but has lower counts in the highest range."
        },
        {
            "id": "q10",
            "number": 10,
            "question": "The mean of the following distribution is 50.<br>x: 10, 30, 50, 70, 90<br>f: 17, 5a+3, 32, 7a-11, 19<br>Find the value of a and hence the frequencies of 30 and 70.",
            "diagram": "<div class=\"q-table-container\"><table class=\"q-table\"><tr><th>x</th><td>10</td><td>30</td><td>50</td><td>70</td><td>90</td></tr><tr><th>f</th><td>17</td><td>5a+3</td><td>32</td><td>7a-11</td><td>19</td></tr></table></div>",
            "answer": "$a = 5$; Frequencies: 28, 24",
            "solution": "Mean $\\bar{x} = \\frac{\\sum f_ix_i}{\\sum f_i} = 50$<br>$\\sum f_i = 17 + (5a+3) + 32 + (7a-11) + 19 = 12a + 60$<br>$\\sum f_ix_i = 10(17) + 30(5a+3) + 50(32) + 70(7a-11) + 90(19)$<br>$= 170 + 150a + 90 + 1600 + 490a - 770 + 1710$<br>$= 640a + 2800$<br>$\\frac{640a + 2800}{12a + 60} = 50$<br>$640a + 2800 = 50(12a + 60)$<br>$640a + 2800 = 600a + 3000$<br>$40a = 200 \\Rightarrow a = 5$<br>Frequency of 30: $5(5)+3 = 28$<br>Frequency of 70: $7(5)-11 = 24$"
        },
        {
            "id": "q11",
            "number": 11,
            "question": "The mean marks (out of 100) of boys and girls in an examination are 70 and 73, respectively. If the mean marks of all the students in that examination is 71, find the ratio of the number of boys to the number of girls.",
            "answer": "2 : 1",
            "solution": "Let number of boys be $n_1$ and girls be $n_2$.<br>Mean of boys $\\bar{x}_1 = 70$, Mean of girls $\\bar{x}_2 = 73$.<br>Combined mean $\\bar{X} = 71$.<br>$\\bar{X} = \\frac{n_1\\bar{x}_1 + n_2\\bar{x}_2}{n_1 + n_2}$<br>$71 = \\frac{70n_1 + 73n_2}{n_1 + n_2}$<br>$71n_1 + 71n_2 = 70n_1 + 73n_2$<br>$n_1 = 2n_2$<br>$\\frac{n_1}{n_2} = \\frac{2}{1}$<br>Ratio of boys to girls is 2:1."
        },
        {
            "id": "q12",
            "number": 12,
            "question": "A total of 25 patients admitted to a hospital are tested for levels of blood sugar, (mg/dl) and the results obtained were as follows:<br>87, 71, 77, 85, 73, 81, 69, 54, 78, 78, 83, 76, 70, 68, 81, 67, 65, 68, 85, 77, 85, 85, 80, 73, 75<br>Find mean, median and mode (mg/dl) of the above data.",
            "answer": "Mean: 75.64, Median: 77, Mode: 85",
            "solution": "Arrange data in ascending order:<br>54, 65, 67, 68, 68, 69, 70, 71, 73, 73, 75, 76, 77, 77, 78, 78, 80, 81, 81, 83, 85, 85, 85, 85, 87<br><strong>Total ($n$) = 25</strong><br><strong>Mean:</strong> $\\frac{\\sum x}{n} = \\frac{1891}{25} = 75.64$<br><strong>Median:</strong> $(\\frac{n+1}{2})^{th}$ term = $13^{th}$ term = 77<br><strong>Mode:</strong> Most frequent value = 85 (occurs 4 times)."
        }
    ]
}