{
    "questions": [
        {
            "id": "q1",
            "number": 1,
            "question": "If two equal chords of a circle intersect, prove that the parts of one chord are separately equal to the parts of the other chord.",
            "answer": "Proof provided below.",
            "solution": "<p><strong>Given:</strong> Two equal chords $AB$ and $CD$ of a circle with centre $O$ intersect at a point $E$ inside the circle.</p><p><strong>To Prove:</strong> $AE = CE$ and $BE = DE$.</p><p><strong>Construction:</strong> Draw $OM \\perp AB$ and $ON \\perp CD$. Join $OE$.</p><p><strong>Proof:</strong><br>In right-angled triangles $\\Delta OME$ and $\\Delta ONE$:<br>1. $OM = ON$ (Equal chords are equidistant from the centre)<br>2. $\\angle OME = \\angle ONE = 90^\\circ$ (By construction)<br>3. $OE = OE$ (Common hypotenuse)<br>$\\therefore \\Delta OME \\cong \\Delta ONE$ (By RHS congruence rule)<br>$\\Rightarrow ME = NE$ (By CPCT) ... (i)</p><p>Since $AB = CD$, dividing both sides by 2:<br>$\\frac{1}{2} AB = \\frac{1}{2} CD$<br>$\\Rightarrow AM = MB = CN = ND$ ... (ii)</p><p>Adding (i) and (ii) for the corresponding parts:<br>$AM + ME = CN + NE$<br>$\\Rightarrow AE = CE$</p><p>Subtracting (i) from (ii) for the remaining parts:<br>$MB - ME = ND - NE$<br>$\\Rightarrow BE = DE$</p><p>Hence proved.</p>"
        },
        {
            "id": "q2",
            "number": 2,
            "question": "If non-parallel sides of a trapezium are equal, prove that it is cyclic.",
            "answer": "Proof provided below.",
            "solution": "<p><strong>Given:</strong> A trapezium $ABCD$ in which $AB \\parallel CD$ and non-parallel sides $AD = BC$.</p><p><strong>To Prove:</strong> $ABCD$ is a cyclic quadrilateral.</p><p><strong>Construction:</strong> Draw $AM \\perp CD$ and $BN \\perp CD$.</p><p><strong>Proof:</strong><br>In $\\Delta AMD$ and $\\Delta BNC$:<br>1. $AD = BC$ (Given)<br>2. $\\angle AMD = \\angle BNC = 90^\\circ$ (By construction)<br>3. $AM = BN$ (Perpendicular distance between parallel lines is constant)<br>$\\therefore \\Delta AMD \\cong \\Delta BNC$ (By RHS congruence rule)<br>$\\Rightarrow \\angle D = \\angle C$ (By CPCT) ... (i)</p><p>Since $AB \\parallel CD$ and $AD$ is a transversal, the sum of consecutive interior angles is $180^\\circ$:<br>$\\angle A + \\angle D = 180^\\circ$</p><p>Substituting $\\angle D$ with $\\angle C$ from (i):<br>$\\angle A + \\angle C = 180^\\circ$</p><p>Since the sum of a pair of opposite angles is $180^\\circ$, the quadrilateral $ABCD$ is cyclic.</p>"
        },
        {
            "id": "q3",
            "number": 3,
            "question": "If $P$, $Q$ and $R$ are the mid-points of the sides $BC$, $CA$ and $AB$ of a triangle and $AD$ is the perpendicular from $A$ on $BC$, prove that $P$, $Q$, $R$ and $D$ are concyclic.",
            "answer": "Proof provided below.",
            "solution": "<p><strong>Given:</strong> $\\Delta ABC$ where $P, Q, R$ are mid-points of $BC, CA, AB$ respectively. $AD \\perp BC$.</p><p><strong>To Prove:</strong> $P, Q, R, D$ are concyclic.</p><p><strong>Proof:</strong><br>In $\\Delta ABC$, $R$ and $Q$ are mid-points of $AB$ and $AC$.<br>By Mid-point Theorem, $RQ \\parallel BC$ and $RQ = \\frac{1}{2}BC$.<br>Since $P$ lies on $BC$, $RQ \\parallel BP$.<br>Similarly, $PQ \\parallel AB$ (By Mid-point Theorem on sides $AC$ and $BC$).<br>Therefore, quadrilateral $BPQR$ is a parallelogram (Opposite sides are parallel).<br>$\\Rightarrow \\angle B = \\angle PQR$ (Opposite angles of a parallelogram are equal) ... (i)</p><p>Now consider the right-angled triangle $\\Delta ABD$ (right angled at $D$).<br>$R$ is the mid-point of hypotenuse $AB$.<br>In a right triangle, the median to the hypotenuse is half the hypotenuse.<br>$\\Rightarrow RD = RA = RB = \\frac{1}{2}AB$.<br>In $\\Delta RBD$, since $RB = RD$, angles opposite to equal sides are equal:<br>$\\Rightarrow \\angle B = \\angle RDB$ ... (ii)</p><p>From (i) and (ii):<br>$\\angle PQR = \\angle RDB$</p><p>Notice that $\\angle RDB$ is the exterior angle at $D$ for the quadrilateral $PQRD$ (if we consider the segment $DP$).<br>Actually, let's look at the segment $RQ$. The points $P$ and $D$ are on the same side of $RQ$.<br>Wait, let's use the property of cyclic quadrilaterals.<br>We found $\\angle PQR = \\angle B$.<br>Also, $PQ \\parallel AB \\Rightarrow PQ \\parallel AR$.<br>$RQ \\parallel BC \\Rightarrow RQ \\parallel DP$.<br>So $ARPQ$ is a parallelogram $\\Rightarrow \\angle A = \\angle RPQ$.<br>In right $\\Delta ABD$, $RD = RA \\Rightarrow \\angle RDA = \\angle RAD = \\angle A$.<br>Thus, $\\angle RPQ = \\angle RDA$.<br>Since the line segment $RQ$ subtends equal angles $\\angle RPQ$ and $\\angle RDQ$ at two points $P$ and $D$ on the same side of it, the points $R, D, P, Q$ are concyclic.</p>"
        },
        {
            "id": "q4",
            "number": 4,
            "question": "$ABCD$ is a parallelogram. A circle through $A$, $B$ is so drawn that it intersects $AD$ at $P$ and $BC$ at $Q$. Prove that $P$, $Q$, $C$, $D$ are concyclic.",
            "answer": "Proof provided below.",
            "solution": "<p><strong>Given:</strong> Parallelogram $ABCD$. A circle passes through $A$ and $B$, cutting $AD$ at $P$ and $BC$ at $Q$.</p><p><strong>To Prove:</strong> $P, Q, C, D$ are concyclic.</p><p><strong>Proof:</strong><br>Since $A, B, Q, P$ lie on a circle, $ABQP$ is a cyclic quadrilateral.<br>In a cyclic quadrilateral, the sum of opposite angles is $180^\\circ$.<br>$\\angle A + \\angle BQP = 180^\\circ$ ... (i)</p><p>Also, for the line segment $BC$, $\\angle BQP$ and $\\angle PQC$ form a linear pair.<br>$\\angle BQP + \\angle PQC = 180^\\circ$ ... (ii)</p><p>From (i) and (ii):<br>$\\angle A = \\angle PQC$ ... (iii)</p><p>Since $ABCD$ is a parallelogram, consecutive interior angles sum to $180^\\circ$:<br>$\\angle A + \\angle D = 180^\\circ$ ... (iv)</p><p>Substituting $\\angle A$ from (iii) into (iv):<br>$\\angle PQC + \\angle D = 180^\\circ$</p><p>In quadrilateral $PQCD$, the sum of the opposite angles ($\\angle PQC$ and $\\angle D$) is $180^\\circ$.<br>Therefore, $PQCD$ is a cyclic quadrilateral, and points $P, Q, C, D$ are concyclic.</p>"
        },
        {
            "id": "q5",
            "number": 5,
            "question": "Prove that angle bisector of any angle of a triangle and perpendicular bisector of the opposite side if intersect, they will intersect on the circumcircle of the triangle.",
            "answer": "Proof provided below.",
            "solution": "<p><strong>Given:</strong> $\\Delta ABC$. $AD$ is the angle bisector of $\\angle A$. $L$ is the perpendicular bisector of side $BC$.</p><p><strong>To Prove:</strong> $AD$ and $L$ intersect on the circumcircle of $\\Delta ABC$.</p><p><strong>Proof:</strong><br>Let the angle bisector of $\\angle A$ intersect the circumcircle at a point $P$.<br>Since $AP$ is the bisector of $\\angle A$, we have:<br>$\\angle BAP = \\angle CAP$</p><p>We know that angles in the same segment of a circle are equal. The arc $BP$ subtends $\\angle BAP$ and the arc $CP$ subtends $\\angle CAP$.<br>Since $\\angle BAP = \\angle CAP$, it implies:<br>$\\text{Arc } BP = \\text{Arc } CP$</p><p>Equal arcs subtend equal chords.<br>$\\Rightarrow \\text{Chord } BP = \\text{Chord } CP$<br>$\\Rightarrow P$ is equidistant from the endpoints $B$ and $C$ of the line segment $BC$.</p><p>We know that the locus of points equidistant from the endpoints of a segment is the perpendicular bisector of that segment.<br>Therefore, point $P$ must lie on the perpendicular bisector of $BC$.</p><p>Thus, the angle bisector of $\\angle A$ and the perpendicular bisector of $BC$ intersect at the point $P$, which lies on the circumcircle.</p>"
        },
        {
            "id": "q6",
            "number": 6,
            "question": "If two chords $AB$ and $CD$ of a circle $AYDZBWCX$ intersect at right angles, prove that $\\text{arc } CXA + \\text{arc } DZB = \\text{arc } AYD + \\text{arc } BWC = \\text{semicircle}$.",
            "diagram": "<svg width=\"350\" height=\"350\" viewBox=\"0 0 350 350\" xmlns=\"http://www.w3.org/2000/svg\"><defs><marker id=\"arrow\" markerWidth=\"6\" markerHeight=\"6\" refX=\"0\" refY=\"3\" orient=\"auto\"><path d=\"M0,0 L0,6 L6,3 z\" fill=\"#000\" /></marker></defs><circle cx=\"175\" cy=\"175\" r=\"100\" stroke=\"black\" fill=\"none\" stroke-width=\"2\"/><circle cx=\"175\" cy=\"175\" r=\"2\" fill=\"black\"/><text x=\"180\" y=\"170\" font-family=\"Arial\" font-size=\"12\">O</text><line x1=\"127.2\" y1=\"87.2\" x2=\"262.8\" y2=\"222.8\" stroke=\"blue\" stroke-width=\"2\"/><text x=\"115\" y=\"85\" font-family=\"Arial\" font-size=\"14\" fill=\"blue\">A</text><text x=\"270\" y=\"235\" font-family=\"Arial\" font-size=\"14\" fill=\"blue\">B</text><line x1=\"104.3\" y1=\"245.7\" x2=\"245.7\" y2=\"104.3\" stroke=\"red\" stroke-width=\"2\"/><text x=\"90\" y=\"260\" font-family=\"Arial\" font-size=\"14\" fill=\"red\">C</text><text x=\"255\" y=\"100\" font-family=\"Arial\" font-size=\"14\" fill=\"red\">D</text><text x=\"200\" y=\"150\" font-family=\"Arial\" font-size=\"12\" font-weight=\"bold\">M</text><path d=\"M 195 155 L 200 160 L 205 155 L 200 150 Z\" fill=\"black\" /><circle cx=\"75\" cy=\"175\" r=\"2\" fill=\"black\"/><text x=\"60\" y=\"180\" font-family=\"Arial\" font-size=\"12\">X</text><circle cx=\"275\" cy=\"175\" r=\"2\" fill=\"black\"/><text x=\"285\" y=\"180\" font-family=\"Arial\" font-size=\"12\">Z</text><text x=\"170\" y=\"65\" font-family=\"Arial\" font-size=\"12\">Y</text><text x=\"170\" y=\"290\" font-family=\"Arial\" font-size=\"12\">W</text></svg>",
            "answer": "Proof provided below.",
            "solution": "<p><strong>Given:</strong> Chords $AB$ and $CD$ intersect at right angles at point $M$.</p><p><strong>To Prove:</strong> $\\text{arc } CXA + \\text{arc } DZB = \\text{semicircle}$.</p><p><strong>Proof:</strong><br>Let the chords intersect at $M$. So $\\angle AMC = 90^\\circ$.<br>Consider the inscribed angles subtended by arcs $AC$ (part of $CXA$) and $BD$ (part of $DZB$).<br>$\\angle ADC$ subtends arc $AC$.<br>$\\angle BAD$ subtends arc $BD$.</p><p>In $\\Delta ADM$:<br>$\\angle M = 90^\\circ \\Rightarrow \\angle ADM + \\angle DAM = 90^\\circ$.<br>$\\angle ADM$ is the angle subtended by arc $AC$ at the circumference.<br>$\\angle DAM$ (same as $\\angle DAB$) is the angle subtended by arc $BD$ at the circumference.</p><p>We know that the angle subtended by an arc at the centre is double the angle at the circumference.<br>Let angles subtended by arc $AC$ and arc $BD$ at centre be $\\theta_1$ and $\\theta_2$.<br>$\\theta_1 = 2 \\angle ADM$<br>$\\theta_2 = 2 \\angle DAM$</p><p>Sum of central angles:<br>$\\theta_1 + \\theta_2 = 2(\\angle ADM + \\angle DAM) = 2(90^\\circ) = 180^\\circ$.</p><p>Since the sum of the angles subtended by arcs $AC$ and $BD$ at the centre is $180^\\circ$, the sum of their lengths constitutes a semicircle.<br>Note: Arc $CXA$ corresponds to arc $AC$ and arc $DZB$ corresponds to arc $BD$ in the context of the figure usually associated with this problem.<br>Therefore, $\\text{arc } CXA + \\text{arc } DZB = \\text{semicircle}$.<br>Similarly, $\\text{arc } AYD + \\text{arc } BWC = \\text{semicircle}$.</p>"
        },
        {
            "id": "q7",
            "number": 7,
            "question": "A circle has radius $\\sqrt{2}$ cm. It is divided into two segments by a chord of length 2 cm. Prove that the angle subtended by the chord at a point in major segment is $45^\\circ$.",
            "answer": "Proof provided below.",
            "solution": "<p><strong>Given:</strong> Circle with centre $O$ and radius $r = \\sqrt{2}$ cm. Chord $AB = 2$ cm.</p><p><strong>To Prove:</strong> Angle in major segment is $45^\\circ$.</p><p><strong>Proof:</strong><br>Consider $\\Delta OAB$.<br>$OA = \\sqrt{2}$ cm<br>$OB = \\sqrt{2}$ cm<br>$AB = 2$ cm</p><p>Check for Pythagoras theorem:<br>$OA^2 + OB^2 = (\\sqrt{2})^2 + (\\sqrt{2})^2 = 2 + 2 = 4$<br>$AB^2 = (2)^2 = 4$<br>Since $OA^2 + OB^2 = AB^2$, $\\Delta OAB$ is a right-angled triangle right angled at $O$.<br>$\\therefore \\angle AOB = 90^\\circ$.</p><p>The angle subtended by an arc at the centre is double the angle subtended by it at any point on the remaining part of the circle (major segment).<br>Let $\\angle APB$ be the angle in the major segment.<br>$\\angle APB = \\frac{1}{2} \\angle AOB$<br>$\\angle APB = \\frac{1}{2} (90^\\circ) = 45^\\circ$.</p><p>Hence proved.</p>"
        },
        {
            "id": "q8",
            "number": 8,
            "question": "Two equal chords $AB$ and $CD$ of a circle when produced intersect at a point $P$. Prove that $PB = PD$.",
            "diagram": "<svg width=\"400\" height=\"300\" viewBox=\"0 0 400 300\" xmlns=\"http://www.w3.org/2000/svg\"><circle cx=\"120\" cy=\"150\" r=\"60\" stroke=\"black\" fill=\"none\" stroke-width=\"2\"/><circle cx=\"120\" cy=\"150\" r=\"2\" fill=\"black\"/><text x=\"110\" y=\"145\" font-family=\"Arial\" font-size=\"12\">O</text><circle cx=\"320\" cy=\"150\" r=\"3\" fill=\"black\"/><text x=\"330\" y=\"155\" font-family=\"Arial\" font-size=\"14\">P</text><line x1=\"320\" y1=\"150\" x2=\"60\" y2=\"111\" stroke=\"black\" stroke-width=\"2\"/><circle cx=\"73\" cy=\"113\" r=\"3\" fill=\"blue\"/><text x=\"65\" y=\"105\" font-family=\"Arial\" font-size=\"14\">A</text><circle cx=\"176\" cy=\"128.4\" r=\"3\" fill=\"blue\"/><text x=\"170\" y=\"120\" font-family=\"Arial\" font-size=\"14\">B</text><line x1=\"320\" y1=\"150\" x2=\"60\" y2=\"189\" stroke=\"black\" stroke-width=\"2\"/><circle cx=\"73\" cy=\"187\" r=\"3\" fill=\"red\"/><text x=\"65\" y=\"205\" font-family=\"Arial\" font-size=\"14\">C</text><circle cx=\"176\" cy=\"171.6\" r=\"3\" fill=\"red\"/><text x=\"170\" y=\"190\" font-family=\"Arial\" font-size=\"14\">D</text><line x1=\"120\" y1=\"150\" x2=\"124.5\" y2=\"120.7\" stroke=\"green\" stroke-dasharray=\"4\"/><text x=\"110\" y=\"125\" font-family=\"Arial\" font-size=\"12\" fill=\"green\">M</text><line x1=\"120\" y1=\"150\" x2=\"124.5\" y2=\"179.3\" stroke=\"green\" stroke-dasharray=\"4\"/><text x=\"110\" y=\"185\" font-family=\"Arial\" font-size=\"12\" fill=\"green\">N</text><line x1=\"120\" y1=\"150\" x2=\"320\" y2=\"150\" stroke=\"gray\" stroke-dasharray=\"2\"/></svg>",
            "answer": "Proof provided below.",
            "solution": "<p><strong>Given:</strong> Two equal chords $AB$ and $CD$ intersect at point $P$ when produced.</p><p><strong>To Prove:</strong> $PB = PD$.</p><p><strong>Construction:</strong> Draw $OM \\perp AB$ and $ON \\perp CD$. Join $OP$.</p><p><strong>Proof:</strong><br>Since $AB = CD$, equal chords are equidistant from the centre.<br>$\\therefore OM = ON$.</p><p>In right-angled triangles $\\Delta OMP$ and $\\Delta ONP$:<br>1. $OM = ON$ (Proved above)<br>2. $\\angle OMP = \\angle ONP = 90^\\circ$ (Construction)<br>3. $OP = OP$ (Common)<br>$\\therefore \\Delta OMP \\cong \\Delta ONP$ (By RHS congruence)<br>$\\Rightarrow MP = NP$ (By CPCT) ... (i)</p><p>We know that a perpendicular from the centre bisects the chord.<br>$AM = MB = \\frac{1}{2}AB$<br>$CN = ND = \\frac{1}{2}CD$<br>Since $AB = CD$, we have $MB = ND$ ... (ii)</p><p>Subtracting (ii) from (i):<br>$MP - MB = NP - ND$<br>$\\Rightarrow PB = PD$.</p><p>Hence proved.</p>"
        },
        {
            "id": "q9",
            "number": 9,
            "question": "$AB$ and $AC$ are two chords of a circle of radius $r$ such that $AB = 2AC$. If $p$ and $q$ are the distances of $AB$ and $AC$ from the centre, prove that $4q^2 = p^2 + 3r^2$.",
            "answer": "Proof provided below.",
            "solution": "<p><strong>Given:</strong> Circle with radius $r$. Chords $AB = 2AC$. Distance of $AB$ from centre is $p$. Distance of $AC$ from centre is $q$.</p><p><strong>To Prove:</strong> $4q^2 = p^2 + 3r^2$.</p><p><strong>Proof:</strong><br>Let $AC = x$. Then $AB = 2x$.<br>Let $M$ be the foot of the perpendicular from centre $O$ to $AB$. $OM = p$.<br>Let $N$ be the foot of the perpendicular from centre $O$ to $AC$. $ON = q$.</p><p>Perpendicular from centre bisects the chord.<br>In $\\Delta OMA$:<br>$AM = \\frac{1}{2}AB = \\frac{1}{2}(2x) = x$.<br>By Pythagoras theorem: $OA^2 = OM^2 + AM^2$<br>$r^2 = p^2 + x^2$ ... (i)</p><p>In $\\Delta ONA$:<br>$AN = \\frac{1}{2}AC = \\frac{x}{2}$.<br>By Pythagoras theorem: $OA^2 = ON^2 + AN^2$<br>$r^2 = q^2 + (\\frac{x}{2})^2$<br>$r^2 = q^2 + \\frac{x^2}{4}$<br>$4r^2 = 4q^2 + x^2$ ... (ii)</p><p>From (i), we have $x^2 = r^2 - p^2$.<br>Substitute $x^2$ in (ii):<br>$4r^2 = 4q^2 + (r^2 - p^2)$<br>$4r^2 - r^2 + p^2 = 4q^2$<br>$3r^2 + p^2 = 4q^2$</p><p>Hence, $4q^2 = p^2 + 3r^2$.</p>"
        },
        {
            "id": "q10",
            "number": 10,
            "question": "If two equal chords $AB$ and $CD$ of a circle intersect at point $P$ inside the circle, prove that the line joining $P$ to the centre $O$ bisects the angle $APD$ and angle $BPC$.",
            "answer": "Proof provided below.",
            "solution": "<p><strong>Given:</strong> Two equal chords $AB$ and $CD$ intersect at $P$. $O$ is the centre.</p><p><strong>To Prove:</strong> $OP$ bisects $\\angle APD$ and $\\angle BPC$.</p><p><strong>Construction:</strong> Draw $OM \\perp AB$ and $ON \\perp CD$.</p><p><strong>Proof:</strong><br>In $\\Delta OMP$ and $\\Delta ONP$:<br>1. $OM = ON$ (Equal chords are equidistant from centre)<br>2. $\\angle OMP = \\angle ONP = 90^\\circ$<br>3. $OP = OP$ (Common)<br>$\\therefore \\Delta OMP \\cong \\Delta ONP$ (RHS)<br>$\\Rightarrow \\angle MPO = \\angle NPO$ (CPCT)<br>$\\Rightarrow OP$ bisects $\\angle APD$.<br>Since $\\angle APD$ and $\\angle BPC$ are vertically opposite angles, the line bisecting one also bisects the other.<br>Hence proved.</p>"
        },
        {
            "id": "q11",
            "number": 11,
            "question": "If two circles intersect at two points $A$ and $B$ and if $AD$ and $AC$ are diameters to the circles, prove that $B$ lies on the line segment $DC$.",
            "answer": "Proof provided below.",
            "solution": "<p><strong>Given:</strong> Two circles intersect at $A, B$. $AD, AC$ are diameters.</p><p><strong>To Prove:</strong> $D, B, C$ are collinear.</p><p><strong>Construction:</strong> Join $AB$.</p><p><strong>Proof:</strong><br>Since $AD$ is a diameter, $\\angle ABD$ is an angle in a semicircle.<br>$\\therefore \\angle ABD = 90^\\circ$.<br>Since $AC$ is a diameter, $\\angle ABC$ is an angle in a semicircle.<br>$\\therefore \\angle ABC = 90^\\circ$.<br>Adding both angles:<br>$\\angle ABD + \\angle ABC = 90^\\circ + 90^\\circ = 180^\\circ$.<br>Since $\\angle DBC = 180^\\circ$, $DBC$ is a straight line.<br>$\\therefore B$ lies on the line segment $DC$.</p>"
        },
        {
            "id": "q12",
            "number": 12,
            "question": "Let the vertex of an angle $ABC$ be located outside a circle and let the sides of the angle intersect equal chords $AD$ and $CE$ with the circle. Prove that $\\angle ABC$ is equal to half the difference of the angles subtended by the chords $AC$ and $DE$ at the centre.",
            "diagram": "<img src=\"/assets/images/classes/class-9/circles/ex-9-4-q12.png\" alt=\"Diagram for Q12\" class=\"img-fluid\">",
            "answer": "Proof provided below.",
            "solution": "<p><strong>Given:</strong> $\\angle ABC$ vertex $B$ is outside. Sides intersect circle at $A, D$ and $C, E$. Chords $AD = CE$.</p><p><strong>To Prove:</strong> $\\angle ABC = \\frac{1}{2} (\\angle DOE - \\angle AOC)$.</p><p><strong>Proof:</strong><br>Join $AC$ and $DE$. Also join $AE$.<br>In $\\Delta ABE$, exterior angle $\\angle DAE = \\angle ABC + \\angle AEC$.<br>$\\Rightarrow \\angle ABC = \\angle DAE - \\angle AEC$.<br>We know that the angle subtended by an arc at the circumference is half the angle at the centre.<br>$\\angle DAE = \\frac{1}{2} \\angle DOE$ (Angle subtended by arc $DE$).<br>$\\angle AEC = \\frac{1}{2} \\angle AOC$ (Angle subtended by arc $AC$).<br>Substituting these values:<br>$\\angle ABC = \\frac{1}{2} \\angle DOE - \\frac{1}{2} \\angle AOC$<br>$\\angle ABC = \\frac{1}{2} (\\angle DOE - \\angle AOC)$.<br>Hence proved.</p>"
        },
        {
            "id": "q13",
            "number": 13,
            "question": "Prove that the circle drawn with any side of a rhombus as diameter, passes through the point of intersection of its diagonals.",
            "answer": "Proof provided below.",
            "solution": "<p><strong>Given:</strong> Rhombus $ABCD$. Circle drawn with side $AB$ as diameter.</p><p><strong>To Prove:</strong> The circle passes through $O$, the intersection of diagonals.</p><p><strong>Proof:</strong><br>We know that the diagonals of a rhombus bisect each other at right angles.<br>$\\therefore \\angle AOB = 90^\\circ$.<br>Consider the circle with diameter $AB$.<br>Since the angle subtended by a diameter at any point on the circle is $90^\\circ$, and $\\angle AOB = 90^\\circ$, the point $O$ must lie on the circle.<br>Therefore, the circle passes through the point of intersection of the diagonals.</p>"
        },
        {
            "id": "q14",
            "number": 14,
            "question": "$ABCD$ is a parallelogram. The circle through $A$, $B$ and $C$ intersect $CD$ (produced if necessary) at $E$. Prove that $AE = AD$.",
            "answer": "Proof provided below.",
            "solution": "<p><strong>Given:</strong> Parallelogram $ABCD$. Circle through $A, B, C$ intersects $CD$ at $E$.</p><p><strong>To Prove:</strong> $AE = AD$.</p><p><strong>Proof:</strong><br>Since $A, B, C, E$ lie on a circle, $ABCE$ is a cyclic quadrilateral.<br>$\\therefore \\angle AEC + \\angle B = 180^\\circ$ (Opposite angles sum to $180^\\circ$).<br>Also, $D, E, C$ is a line, so $\\angle AEC + \\angle AED = 180^\\circ$ (Linear pair).<br>From these two, $\\angle AED = \\angle B$.<br>Since $ABCD$ is a parallelogram, opposite angles are equal.<br>$\\therefore \\angle B = \\angle D$ (i.e., $\\angle ADC$).<br>So, $\\angle AED = \\angle ADC$.<br>In $\\Delta ADE$, since $\\angle AED = \\angle ADE$, the sides opposite to them are equal.<br>$\\therefore AE = AD$.<br>Hence proved.</p>"
        }
    ]
}